singular_tweaks/__init__.py
singular_tweaks/core.py
singular_tweaks-1.0.8.dist-info/METADATA
singular_tweaks-1.0.8.dist-info/WHEEL
singular_tweaks-1.0.8.dist-info/top_level.txt
singular_tweaks-1.0.8.dist-info/RECORD
