Metadata-Version: 2.4
Name: singular-tweaks
Version: 1.0.8
Summary: Helper UI and HTTP API for Singular.live + optional TfL data
Author-email: BlueElliott <elliott.ramdass10@gmail.com>
License: MIT
Project-URL: Homepage, https://github.com/ramdasse/Singular-Tweaks
Project-URL: Repository, https://github.com/ramdasse/Singular-Tweaks.git
Project-URL: Issues, https://github.com/ramdasse/Singular-Tweaks/issues
Keywords: singular,tfl,fastapi
Classifier: Programming Language :: Python :: 3
Classifier: Programming Language :: Python :: 3.8
Classifier: Programming Language :: Python :: 3.9
Classifier: Programming Language :: Python :: 3.10
Classifier: Programming Language :: Python :: 3.11
Classifier: License :: OSI Approved :: MIT License
Requires-Python: >=3.8
Requires-Dist: fastapi>=0.100.0
Requires-Dist: uvicorn[standard]>=0.23.0
Requires-Dist: requests>=2.28.0
Requires-Dist: pydantic>=2.0.0
Provides-Extra: dev
Requires-Dist: pytest>=7.0; extra == "dev"
Requires-Dist: black>=23.0; extra == "dev"
Requires-Dist: ruff>=0.1.0; extra == "dev"
